[
  {
    "id": 1,
    "name": "Mariam",
    "age": 34,
    "gender": "female",
    "status": true,
    "creation_timestamp": "2016-11-28T14:10:11.338Z",
    "modification_timestamp": "1688980086770"
  },
  {
    "name": "Areg",
    "id": 4,
    "age": 35,
    "gender": "male",
    "status": true,
    "creation_timestamp": "1688970605277"
  },
  {
    "name": "Yeranush",
    "id": 6,
    "age": 29,
    "gender": "female",
    "status": true,
    "creation_timestamp": "1688978991401",
    "modification_timestamp": "1688979607350"
  },
  {
    "name": "Yeranush",
    "id": 6,
    "age": 29,
    "gender": "female",
    "status": false,
    "creation_timestamp": "1688980956663",
    "modification_timestamp": "1688980956663"
  }
]